quri_parts/qiskit/NOTICE
quri_parts/qiskit/__init__.py
quri_parts/qiskit/backend/__init__.py
quri_parts/qiskit/backend/connectivity.py
quri_parts/qiskit/backend/primitive.py
quri_parts/qiskit/backend/sampling.py
quri_parts/qiskit/backend/saved_sampling.py
quri_parts/qiskit/backend/tracker.py
quri_parts/qiskit/backend/utils.py
quri_parts/qiskit/circuit/__init__.py
quri_parts/qiskit/circuit/circuit_converter.py
quri_parts/qiskit/circuit/qiskit_circuit_converter.py
quri_parts/qiskit/circuit/transpile/__init__.py
quri_parts/qiskit/operator/__init__.py
quri_parts/qiskit/py.typed
quri_parts_qiskit-17.0.0.dist-info/LICENSE
quri_parts_qiskit-17.0.0.dist-info/METADATA
quri_parts_qiskit-17.0.0.dist-info/WHEEL
quri_parts_qiskit-17.0.0.dist-info/RECORD
